<annotation>
	<folder>imgs</folder>
	<filename>file_0_original.jpg</filename>
	<path>Path_to_change/imgs/file_0_original.jpg</path>
	<source>
		<database>Unknown</database>
	</source>
	<size>
		<width>266</width>
		<height>516</height>
		<depth>3</depth>
	</size>
	<segmented>0</segmented>
	<object>
		<name>Logo</name>
		<pose>Unspecified</pose>
		<truncated>0</truncated>
		<difficult>0</difficult>
		<bndbox>
			<xmin>24</xmin>
			<ymin>52</ymin>
			<xmax>240</xmax>
			<ymax>124</ymax>
		</bndbox>
	</object>
	<object>
		<name>Shop details</name>
		<pose>Unspecified</pose>
		<truncated>0</truncated>
		<difficult>0</difficult>
		<bndbox>
			<xmin>20</xmin>
			<ymin>126</ymin>
			<xmax>242</xmax>
			<ymax>184</ymax>
		</bndbox>
	</object>
	<object>
		<name>Purchase summary</name>
		<pose>Unspecified</pose>
		<truncated>0</truncated>
		<difficult>0</difficult>
		<bndbox>
			<xmin>15</xmin>
			<ymin>184</ymin>
			<xmax>244</xmax>
			<ymax>444</ymax>
		</bndbox>
	</object>
	<object>
		<name>Additional details</name>
		<pose>Unspecified</pose>
		<truncated>0</truncated>
		<difficult>0</difficult>
		<bndbox>
			<xmin>10</xmin>
			<ymin>445</ymin>
			<xmax>244</xmax>
			<ymax>476</ymax>
		</bndbox>
	</object>
	<object>
		<name>Receipt</name>
		<pose>Unspecified</pose>
		<truncated>0</truncated>
		<difficult>0</difficult>
		<bndbox>
			<xmin>13</xmin>
			<ymin>31</ymin>
			<xmax>247</xmax>
			<ymax>481</ymax>
		</bndbox>
	</object>
</annotation>
